pytest_aiohttp/__init__.py
pytest_aiohttp/_version.py
pytest_aiohttp/plugin.py
pytest_aiohttp-1.0.5.dist-info/LICENSE
pytest_aiohttp-1.0.5.dist-info/METADATA
pytest_aiohttp-1.0.5.dist-info/WHEEL
pytest_aiohttp-1.0.5.dist-info/entry_points.txt
pytest_aiohttp-1.0.5.dist-info/top_level.txt
pytest_aiohttp-1.0.5.dist-info/RECORD
