Metadata-Version: 2.1
Name: pytest-aiohttp
Version: 1.0.5
Summary: Pytest plugin for aiohttp support
Home-page: https://github.com/aio-libs/pytest-aiohttp
Maintainer: aiohttp team <team@aiohttp.org>
Maintainer-email: team@aiohttp.org
License: Apache 2.0
Project-URL: GitHub, https://github.com/aio-libs/pytest-aiohttp
Project-URL: Changelog, https://github.com/aio-libs/pytest-aiohttp/blob/master/CHANGES.rst
Classifier: Development Status :: 4 - Beta
Classifier: Intended Audience :: Developers
Classifier: License :: OSI Approved :: Apache Software License
Classifier: Programming Language :: Python :: 3.7
Classifier: Programming Language :: Python :: 3.8
Classifier: Programming Language :: Python :: 3.9
Classifier: Programming Language :: Python :: 3.10
Classifier: Topic :: Software Development :: Testing
Classifier: Framework :: AsyncIO
Classifier: Framework :: Pytest
Classifier: Framework :: aiohttp
Classifier: Typing :: Typed
Requires-Python: >=3.7
Provides-Extra: testing
License-File: LICENSE
